grocer.py
grocer-0.1.0.dist-info/LICENSE
grocer-0.1.0.dist-info/WHEEL
grocer-0.1.0.dist-info/METADATA
grocer-0.1.0.dist-info/RECORD
